kwp2txt/__init__.py
kwp2txt/__main__.py
kwp2txt/version.py
kwp2txt-0.0.1.dist-info/METADATA
kwp2txt-0.0.1.dist-info/WHEEL
kwp2txt-0.0.1.dist-info/entry_points.txt
kwp2txt-0.0.1.dist-info/top_level.txt
kwp2txt-0.0.1.dist-info/RECORD
