Metadata-Version: 2.4
Name: kwp2txt
Version: 0.0.1
Summary: Tool for converting Kamban word processor (KWP) files
Author-email: Jabez Winston <jabezwinston@gmail.com>
License-Expression: MIT
Project-URL: Source code, https://github.com/jabezwinston/kwp2txt
Keywords: tamil,kamban,kwp
Classifier: Programming Language :: Python :: 3
Classifier: Operating System :: Microsoft :: Windows
Classifier: Operating System :: POSIX :: Linux
Classifier: Operating System :: MacOS :: MacOS X
Requires-Python: >=3.8
